leeladoc/__init__.py
leeladoc/__main__.py
leeladoc/debug.py
leeladoc/release.py
leeladoc/api/metrics.py
leeladoc/api/pages.py
leeladoc/api/status.py
leeladoc/api/pages/__init__.py
leeladoc/api/pages/name/version/upload.py
leela_doc-0.9.1.dist-info/LICENSE
leela_doc-0.9.1.dist-info/METADATA
leela_doc-0.9.1.dist-info/WHEEL
leela_doc-0.9.1.dist-info/top_level.txt
leela_doc-0.9.1.dist-info/zip-safe
leela_doc-0.9.1.dist-info/RECORD
