Metadata-Version: 2.1
Name: leela-doc
Version: 0.9.1
Summary: Minimal viable project documentation publishing site
Author-email: Julien Lecomte <julien@lecomte.at>
License: MIT
Project-URL: Homepage, https://gitlab.com/jlecomte/python/leela-doc
Project-URL: Documentation, https://jlecomte.gitlab.io/python/leeladoc/
Project-URL: Source code, https://gitlab.com/jlecomte/python/leela-doc
Project-URL: Bug tracker, https://gitlab.com/jlecomte/python/leela-doc/-/issues
Classifier: License :: OSI Approved :: MIT License
Classifier: Intended Audience :: Developers
Classifier: Development Status :: 3 - Alpha
Classifier: Programming Language :: Python :: 3 :: Only
Classifier: Programming Language :: Python :: 3.7
Classifier: Programming Language :: Python :: 3.8
Classifier: Programming Language :: Python :: 3.9
Requires-Python: >=3.7
License-File: LICENSE
Requires-Dist: filelock
Requires-Dist: flasket
Requires-Dist: python-magic
